{
  "models" : {
    "Deer Feeder" : {
      "mtl" : "Models\/Deer Feeder\/deer_feeder.mtl",
      "obj" : "Models\/Deer Feeder\/deer_feeder.obj"
    },
    "Straw Bale Frame Detail" : {
      "mtl" : "Models\/Straw Bale Frame Detail\/Straw Bale Frame Detail.mtl",
      "obj" : "Models\/Straw Bale Frame Detail\/Straw Bale Frame Detail.obj"
    },
    "house test" : {
      "obj" : "Models\/house test\/house test.obj",
      "mtl" : "Models\/house test\/house test.mtl"
    },
    "Straw Bale Detail 1" : {
      "obj" : "Models\/Straw Bale Detail 1\/Straw Bale Detail 1.obj",
      "mtl" : "Models\/Straw Bale Detail 1\/Straw Bale Detail 1.mtl"
    },
    "Thor Final" : {
      "obj" : "Models\/Thor Final\/Thor Final.obj",
      "mtl" : "Models\/Thor Final\/Thor Final.mtl"
    },
    "Coil" : {
      "mtl" : "Models\/Coil\/Coil.mtl",
      "obj" : "Models\/Coil\/Coil.obj"
    }
  }
}